{
    "Customer_ID": "CUST_0142",
    "Transactions": [
        {
            "Category": "Transportation",
            "Item": "Public Transit",
            "Quantity": 1,
            "Price Per Unit": 5.12,
            "Total Spent": 5.12,
            "Payment Method": "Debit Card",
            "Location": "Mobile App",
            "Transaction Date": "03/02/2024"
        },
        {
            "Category": "Gifts",
            "Item": "Flowers",
            "Quantity": 2,
            "Price Per Unit": 31.72,
            "Total Spent": 63.45,
            "Payment Method": "Debit Card",
            "Location": "Mobile App",
            "Transaction Date": "21/02/2023"
        },
        {
            "Category": "Housing and Utilities",
            "Item": "Electricity Bill",
            "Quantity": 1,
            "Price Per Unit": 118.97,
            "Total Spent": 118.97,
            "Payment Method": "Credit Card",
            "Location": "Online",
            "Transaction Date": "15/12/2024"
        },
        {
            "Category": "Friend Activities",
            "Item": "Concert Tickets",
            "Quantity": 5,
            "Price Per Unit": 146.35,
            "Total Spent": 731.73,
            "Payment Method": "Digital Wallet",
            "Location": "Mobile App",
            "Transaction Date": "24/05/2023"
        },
        {
            "Category": "Friend Activities",
            "Item": "Concert Tickets",
            "Quantity": 4,
            "Price Per Unit": 198.54,
            "Total Spent": 794.17,
            "Payment Method": "Credit Card",
            "Location": "In-store",
            "Transaction Date": "03/02/2023"
        },
        {
            "Category": "Fitness",
            "Item": "Personal Trainer",
            "Quantity": 4,
            "Price Per Unit": 84.99,
            "Total Spent": 339.95,
            "Payment Method": "Credit Card",
            "Location": "Online",
            "Transaction Date": "06/12/2023"
        },
        {
            "Category": "Shopping",
            "Item": "Car",
            "Quantity": 4,
            "Price Per Unit": 44355.26,
            "Total Spent": 177421.04,
            "Payment Method": "Cash",
            "Location": "Online",
            "Transaction Date": "22/04/2024"
        },
        {
            "Category": "Gifts",
            "Item": "Jewelry",
            "Quantity": 1,
            "Price Per Unit": 207.57,
            "Total Spent": 207.57,
            "Payment Method": "Cash",
            "Location": "Mobile App",
            "Transaction Date": "08/11/2023"
        },
        {
            "Category": "Subscriptions",
            "Item": "Gym Membership",
            "Quantity": 1,
            "Price Per Unit": 61.49,
            "Total Spent": 61.49,
            "Payment Method": "Cash",
            "Location": "Online",
            "Transaction Date": "16/06/2024"
        },
        {
            "Category": "Gifts",
            "Item": "Kids Games",
            "Quantity": 4,
            "Price Per Unit": 89.29,
            "Total Spent": 357.17,
            "Payment Method": "Digital Wallet",
            "Location": "In-store",
            "Transaction Date": "12/11/2024"
        },
        {
            "Category": "Shopping",
            "Item": "Clothes",
            "Quantity": 3,
            "Price Per Unit": 111.99,
            "Total Spent": 335.98,
            "Payment Method": "Credit Card",
            "Location": "Online",
            "Transaction Date": "13/05/2023"
        },
        {
            "Category": "Subscriptions",
            "Item": "Streaming Service",
            "Quantity": 1,
            "Price Per Unit": 17.37,
            "Total Spent": 17.37,
            "Payment Method": "Cash",
            "Location": "In-store",
            "Transaction Date": "04/01/2024"
        },
        {
            "Category": "Fitness",
            "Item": "Workout Equipment",
            "Quantity": 2,
            "Price Per Unit": 66.04,
            "Total Spent": 132.08,
            "Payment Method": "Credit Card",
            "Location": "In-store",
            "Transaction Date": "03/11/2023"
        },
        {
            "Category": "Personal Hygiene",
            "Item": "Skin Care Products",
            "Quantity": 2,
            "Price Per Unit": 556.48,
            "Total Spent": 1112.95,
            "Payment Method": "Digital Wallet",
            "Location": "In-store",
            "Transaction Date": "22/12/2023"
        },
        {
            "Category": "Personal Hygiene",
            "Item": "Soap",
            "Quantity": 3,
            "Price Per Unit": 5.7,
            "Total Spent": 17.1,
            "Payment Method": "Cash",
            "Location": "Online",
            "Transaction Date": "03/08/2024"
        },
        {
            "Category": "Groceries",
            "Item": "Fruits",
            "Quantity": 4,
            "Price Per Unit": 3.94,
            "Total Spent": 15.77,
            "Payment Method": "Digital Wallet",
            "Location": "Mobile App",
            "Transaction Date": "09/10/2023"
        },
        {
            "Category": "Fitness",
            "Item": "Yoga Class",
            "Quantity": 1,
            "Price Per Unit": 20.44,
            "Total Spent": 20.44,
            "Payment Method": "Credit Card",
            "Location": "In-store",
            "Transaction Date": "09/06/2023"
        },
        {
            "Category": "Travel",
            "Item": "Taxi/Uber",
            "Quantity": 1,
            "Price Per Unit": 37.49,
            "Total Spent": 37.49,
            "Payment Method": "Credit Card",
            "Location": "Online",
            "Transaction Date": "15/07/2023"
        },
        {
            "Category": "Hobbies",
            "Item": "Art Supplies",
            "Quantity": 3,
            "Price Per Unit": 74.93,
            "Total Spent": 224.79,
            "Payment Method": "Debit Card",
            "Location": "In-store",
            "Transaction Date": "02/10/2023"
        },
        {
            "Category": "Hobbies",
            "Item": "Books",
            "Quantity": 3,
            "Price Per Unit": 30.79,
            "Total Spent": 92.37,
            "Payment Method": "Debit Card",
            "Location": "Online",
            "Transaction Date": "11/12/2024"
        },
        {
            "Category": "Shopping",
            "Item": "Electronics",
            "Quantity": 1,
            "Price Per Unit": 141.94,
            "Total Spent": 141.94,
            "Payment Method": "Digital Wallet",
            "Location": "In-store",
            "Transaction Date": "10/09/2023"
        },
        {
            "Category": "Hobbies",
            "Item": "Books",
            "Quantity": 4,
            "Price Per Unit": 40.75,
            "Total Spent": 163.0,
            "Payment Method": "Cash",
            "Location": "Online",
            "Transaction Date": "18/12/2024"
        },
        {
            "Category": "Travel",
            "Item": "Hotel Stay",
            "Quantity": 1,
            "Price Per Unit": 126.2,
            "Total Spent": 126.2,
            "Payment Method": "Digital Wallet",
            "Location": "Online",
            "Transaction Date": "12/01/2025"
        },
        {
            "Category": "Personal Hygiene",
            "Item": "Soap",
            "Quantity": 4,
            "Price Per Unit": 6.94,
            "Total Spent": 27.77,
            "Payment Method": "Credit Card",
            "Location": "In-store",
            "Transaction Date": "02/04/2024"
        },
        {
            "Category": "Medical/Dental",
            "Item": "Doctor Visit",
            "Quantity": 1,
            "Price Per Unit": 127.12,
            "Total Spent": 127.12,
            "Payment Method": "Digital Wallet",
            "Location": "Online",
            "Transaction Date": "05/12/2023"
        },
        {
            "Category": "Subscriptions",
            "Item": "Gym Membership",
            "Quantity": 1,
            "Price Per Unit": 51.03,
            "Total Spent": 51.03,
            "Payment Method": "Digital Wallet",
            "Location": "In-store",
            "Transaction Date": "11/02/2024"
        },
        {
            "Category": "Fitness",
            "Item": "Workout Equipment",
            "Quantity": 3,
            "Price Per Unit": 429.58,
            "Total Spent": 1288.73,
            "Payment Method": "Credit Card",
            "Location": "In-store",
            "Transaction Date": "06/01/2025"
        },
        {
            "Category": "Transportation",
            "Item": "Public Transit",
            "Quantity": 1,
            "Price Per Unit": 8.04,
            "Total Spent": 8.04,
            "Payment Method": "Debit Card",
            "Location": "In-store",
            "Transaction Date": "04/04/2024"
        },
        {
            "Category": "Gifts",
            "Item": "Gift Cards",
            "Quantity": 4,
            "Price Per Unit": 82.41,
            "Total Spent": 329.65,
            "Payment Method": "Cash",
            "Location": "Mobile App",
            "Transaction Date": "14/05/2024"
        },
        {
            "Category": "Groceries",
            "Item": "Milk",
            "Quantity": 4,
            "Price Per Unit": 4.95,
            "Total Spent": 19.79,
            "Payment Method": "Digital Wallet",
            "Location": "In-store",
            "Transaction Date": "23/11/2023"
        },
        {
            "Category": "Groceries",
            "Item": "Snacks",
            "Quantity": 4,
            "Price Per Unit": 8.57,
            "Total Spent": 34.29,
            "Payment Method": "Cash",
            "Location": "Online",
            "Transaction Date": "26/10/2023"
        },
        {
            "Category": "Gifts",
            "Item": "Jewelry",
            "Quantity": 2,
            "Price Per Unit": 101.77,
            "Total Spent": 203.54,
            "Payment Method": "Debit Card",
            "Location": "Mobile App",
            "Transaction Date": "13/02/2024"
        },
        {
            "Category": "Groceries",
            "Item": "Bread",
            "Quantity": 1,
            "Price Per Unit": 1.49,
            "Total Spent": 1.49,
            "Payment Method": "Debit Card",
            "Location": "Online",
            "Transaction Date": "10/02/2023"
        },
        {
            "Category": "Friend Activities",
            "Item": "Dinner with Friends",
            "Quantity": 3,
            "Price Per Unit": 56.99,
            "Total Spent": 170.98,
            "Payment Method": "Digital Wallet",
            "Location": "Online",
            "Transaction Date": "12/07/2023"
        },
        {
            "Category": "Personal Hygiene",
            "Item": "Skin Care Products",
            "Quantity": 3,
            "Price Per Unit": 530.3,
            "Total Spent": 1590.9,
            "Payment Method": "Digital Wallet",
            "Location": "Mobile App",
            "Transaction Date": "01/09/2024"
        },
        {
            "Category": "Medical/Dental",
            "Item": "Dentist Visit",
            "Quantity": 1,
            "Price Per Unit": 201.5,
            "Total Spent": 201.5,
            "Payment Method": "Digital Wallet",
            "Location": "Mobile App",
            "Transaction Date": "20/02/2023"
        },
        {
            "Category": "Friend Activities",
            "Item": "Concert Tickets",
            "Quantity": 2,
            "Price Per Unit": 177.01,
            "Total Spent": 354.02,
            "Payment Method": "Credit Card",
            "Location": "Online",
            "Transaction Date": "29/12/2023"
        },
        {
            "Category": "Gifts",
            "Item": "Jewelry",
            "Quantity": 5,
            "Price Per Unit": 488.45,
            "Total Spent": 2442.23,
            "Payment Method": "Digital Wallet",
            "Location": "In-store",
            "Transaction Date": "09/02/2023"
        },
        {
            "Category": "Medical/Dental",
            "Item": "Medicine",
            "Quantity": 1,
            "Price Per Unit": 664.56,
            "Total Spent": 664.56,
            "Payment Method": "Debit Card",
            "Location": "In-store",
            "Transaction Date": "01/09/2024"
        },
        {
            "Category": "Medical/Dental",
            "Item": "Medicine",
            "Quantity": 1,
            "Price Per Unit": 517.96,
            "Total Spent": 517.96,
            "Payment Method": "Cash",
            "Location": "Online",
            "Transaction Date": "13/09/2023"
        },
        {
            "Category": "Personal Hygiene",
            "Item": "Shampoo",
            "Quantity": 5,
            "Price Per Unit": 12.76,
            "Total Spent": 63.82,
            "Payment Method": "Cash",
            "Location": "Online",
            "Transaction Date": "13/08/2023"
        },
        {
            "Category": "Personal Hygiene",
            "Item": "Soap",
            "Quantity": 5,
            "Price Per Unit": 6.9,
            "Total Spent": 34.52,
            "Payment Method": "Cash",
            "Location": "Mobile App",
            "Transaction Date": "14/08/2023"
        },
        {
            "Category": "Friend Activities",
            "Item": "Dinner with Friends",
            "Quantity": 4,
            "Price Per Unit": 64.64,
            "Total Spent": 258.57,
            "Payment Method": "Credit Card",
            "Location": "In-store",
            "Transaction Date": "12/06/2023"
        },
        {
            "Category": "Travel",
            "Item": "Taxi/Uber",
            "Quantity": 1,
            "Price Per Unit": 45.91,
            "Total Spent": 45.91,
            "Payment Method": "Debit Card",
            "Location": "Online",
            "Transaction Date": "16/02/2023"
        },
        {
            "Category": "Food",
            "Item": "Restaurant Meal",
            "Quantity": 1,
            "Price Per Unit": 80.13,
            "Total Spent": 80.13,
            "Payment Method": "Digital Wallet",
            "Location": "Mobile App",
            "Transaction Date": "06/10/2024"
        },
        {
            "Category": "Hobbies",
            "Item": "Art Supplies",
            "Quantity": 5,
            "Price Per Unit": 59.29,
            "Total Spent": 296.46,
            "Payment Method": "Credit Card",
            "Location": "Mobile App",
            "Transaction Date": "14/01/2024"
        },
        {
            "Category": "Friend Activities",
            "Item": "Dinner with Friends",
            "Quantity": 3,
            "Price Per Unit": 48.82,
            "Total Spent": 146.47,
            "Payment Method": "Credit Card",
            "Location": "Online",
            "Transaction Date": "14/11/2023"
        },
        {
            "Category": "Groceries",
            "Item": "Vegetables",
            "Quantity": 4,
            "Price Per Unit": 5.57,
            "Total Spent": 22.26,
            "Payment Method": "Credit Card",
            "Location": "In-store",
            "Transaction Date": "24/01/2024"
        },
        {
            "Category": "Subscriptions",
            "Item": "Gym Membership",
            "Quantity": 1,
            "Price Per Unit": 37.41,
            "Total Spent": 37.41,
            "Payment Method": "Credit Card",
            "Location": "Mobile App",
            "Transaction Date": "17/05/2023"
        },
        {
            "Category": "Fitness",
            "Item": "Personal Trainer",
            "Quantity": 2,
            "Price Per Unit": 119.83,
            "Total Spent": 239.65,
            "Payment Method": "Cash",
            "Location": "Online",
            "Transaction Date": "05/01/2025"
        },
        {
            "Category": "Food",
            "Item": "Restaurant Meal",
            "Quantity": 4,
            "Price Per Unit": 15.55,
            "Total Spent": 62.2,
            "Payment Method": "Credit Card",
            "Location": "Mobile App",
            "Transaction Date": "11/10/2024"
        },
        {
            "Category": "Medical/Dental",
            "Item": "Medicine",
            "Quantity": 1,
            "Price Per Unit": 154.29,
            "Total Spent": 154.29,
            "Payment Method": "Credit Card",
            "Location": "In-store",
            "Transaction Date": "17/12/2024"
        },
        {
            "Category": "Travel",
            "Item": "Plane Ticket",
            "Quantity": 1,
            "Price Per Unit": 1325.56,
            "Total Spent": 1325.56,
            "Payment Method": "Credit Card",
            "Location": "Online",
            "Transaction Date": "14/02/2024"
        },
        {
            "Category": "Personal Hygiene",
            "Item": "Toothpaste",
            "Quantity": 4,
            "Price Per Unit": 3.82,
            "Total Spent": 15.28,
            "Payment Method": "Debit Card",
            "Location": "Online",
            "Transaction Date": "04/01/2023"
        },
        {
            "Category": "Fitness",
            "Item": "Yoga Class",
            "Quantity": 4,
            "Price Per Unit": 27.74,
            "Total Spent": 110.96,
            "Payment Method": "Cash",
            "Location": "Online",
            "Transaction Date": "17/04/2023"
        },
        {
            "Category": "Fitness",
            "Item": "Personal Trainer",
            "Quantity": 2,
            "Price Per Unit": 91.91,
            "Total Spent": 183.83,
            "Payment Method": "Credit Card",
            "Location": "In-store",
            "Transaction Date": "21/10/2024"
        },
        {
            "Category": "Food",
            "Item": "Restaurant Meal",
            "Quantity": 5,
            "Price Per Unit": 51.55,
            "Total Spent": 257.75,
            "Payment Method": "Credit Card",
            "Location": "In-store",
            "Transaction Date": "11/12/2023"
        },
        {
            "Category": "Shopping",
            "Item": "Car",
            "Quantity": 4,
            "Price Per Unit": 10099.35,
            "Total Spent": 40397.4,
            "Payment Method": "Digital Wallet",
            "Location": "In-store",
            "Transaction Date": "11/10/2023"
        },
        {
            "Category": "Transportation",
            "Item": "Gas",
            "Quantity": 1,
            "Price Per Unit": 38.11,
            "Total Spent": 38.11,
            "Payment Method": "Debit Card",
            "Location": "In-store",
            "Transaction Date": "08/12/2024"
        },
        {
            "Category": "Housing and Utilities",
            "Item": "Gas Bill",
            "Quantity": 1,
            "Price Per Unit": 96.62,
            "Total Spent": 96.62,
            "Payment Method": "Cash",
            "Location": "Online",
            "Transaction Date": "10/02/2024"
        },
        {
            "Category": "Gifts",
            "Item": "Kids Games",
            "Quantity": 4,
            "Price Per Unit": 67.3,
            "Total Spent": 269.19,
            "Payment Method": "Credit Card",
            "Location": "Mobile App",
            "Transaction Date": "08/06/2024"
        },
        {
            "Category": "Gifts",
            "Item": "Kids Games",
            "Quantity": 4,
            "Price Per Unit": 99.68,
            "Total Spent": 398.7,
            "Payment Method": "Cash",
            "Location": "Mobile App",
            "Transaction Date": "13/04/2024"
        },
        {
            "Category": "Groceries",
            "Item": "Meat",
            "Quantity": 4,
            "Price Per Unit": 22.66,
            "Total Spent": 90.63,
            "Payment Method": "Digital Wallet",
            "Location": "Mobile App",
            "Transaction Date": "11/01/2024"
        },
        {
            "Category": "Groceries",
            "Item": "Meat",
            "Quantity": 4,
            "Price Per Unit": 17.46,
            "Total Spent": 69.82,
            "Payment Method": "Debit Card",
            "Location": "Mobile App",
            "Transaction Date": "08/06/2024"
        },
        {
            "Category": "Personal Hygiene",
            "Item": "Shampoo",
            "Quantity": 4,
            "Price Per Unit": 13.09,
            "Total Spent": 52.34,
            "Payment Method": "Debit Card",
            "Location": "Online",
            "Transaction Date": "05/05/2024"
        },
        {
            "Category": "Groceries",
            "Item": "Milk",
            "Quantity": 4,
            "Price Per Unit": 3.2,
            "Total Spent": 12.79,
            "Payment Method": "Debit Card",
            "Location": "In-store",
            "Transaction Date": "25/05/2024"
        },
        {
            "Category": "Fitness",
            "Item": "Yoga Class",
            "Quantity": 1,
            "Price Per Unit": 19.8,
            "Total Spent": 19.8,
            "Payment Method": "Cash",
            "Location": "Online",
            "Transaction Date": "26/07/2023"
        },
        {
            "Category": "Travel",
            "Item": "Hotel Stay",
            "Quantity": 1,
            "Price Per Unit": 85.86,
            "Total Spent": 85.86,
            "Payment Method": "Debit Card",
            "Location": "Online",
            "Transaction Date": "10/06/2024"
        },
        {
            "Category": "Groceries",
            "Item": "Chicken",
            "Quantity": 5,
            "Price Per Unit": 11.56,
            "Total Spent": 57.8,
            "Payment Method": "Cash",
            "Location": "In-store",
            "Transaction Date": "17/02/2024"
        },
        {
            "Category": "Fitness",
            "Item": "Personal Trainer",
            "Quantity": 3,
            "Price Per Unit": 121.29,
            "Total Spent": 363.86,
            "Payment Method": "Debit Card",
            "Location": "In-store",
            "Transaction Date": "05/03/2024"
        },
        {
            "Category": "Hobbies",
            "Item": "Art Supplies",
            "Quantity": 1,
            "Price Per Unit": 14.7,
            "Total Spent": 14.7,
            "Payment Method": "Credit Card",
            "Location": "Mobile App",
            "Transaction Date": "28/12/2023"
        },
        {
            "Category": "Shopping",
            "Item": "Electronics",
            "Quantity": 2,
            "Price Per Unit": 220.96,
            "Total Spent": 441.92,
            "Payment Method": "Digital Wallet",
            "Location": "Mobile App",
            "Transaction Date": "19/01/2024"
        }
    ]
}